printype/__init__.py
printype/printype.py
printype-0.0.1.dist-info/licenses/LICENSE
printype-0.0.1.dist-info/METADATA
printype-0.0.1.dist-info/WHEEL
printype-0.0.1.dist-info/top_level.txt
printype-0.0.1.dist-info/RECORD
