Metadata-Version: 2.4
Name: printype
Version: 0.0.1
Summary: 6 useful functions for better debbuging. The best are printype_symbol and typering_symbol
Author-email: Mohammad Pourmohammadi Fallah <mohammad.pfallah@gmail.com>, Fatemeh Motamed <motamed.258@gmail.com>
License-Expression: MIT
Project-URL: Homepage, https://github.com/pypa/sampleproject
Project-URL: Issues, https://github.com/pypa/sampleproject/issues
Classifier: Programming Language :: Python :: 3
Classifier: Operating System :: OS Independent
Requires-Python: >=3.9
License-File: LICENSE
Dynamic: license-file
